coininfo_abu/__init__.py
coininfo_abu/info.py
coininfo_abu-0.2.dist-info/METADATA
coininfo_abu-0.2.dist-info/WHEEL
coininfo_abu-0.2.dist-info/top_level.txt
coininfo_abu-0.2.dist-info/RECORD
