Metadata-Version: 2.1
Name: coininfo-abu
Version: 0.2
Requires-Dist: request ==2.31.0
